{
    "tasks": [
        {
            "id": 1,
            "title": "Yugurish",
            "description": "ertalab 6:00 da 3 km yugurish",
            "status": false
        },
        {
            "id": 2,
            "title": "Kitob oqish",
            "description": "ertalab 7:00 da 30 minute kitob oqish",
            "status": false
        },
        {
            "id": 3,
            "title": "Study",
            "description": "9:00 da oqishga ketishim kerak",
            "status": false
        },
        {
            "id": 4,
            "title": "test",
            "description": "test",
            "status": false
        },
        {
            "id": 5,
            "title": "test 2",
            "description": "test 2",
            "status": false
        },
        {
            "id": 6,
            "title": "kitob o'qish",
            "description": "soat 9da",
            "status": false
        }
    ],
    "current_id": 7
}